{
  "start": {
    "frage": "Damit ich passende Förderprogramme finden kann, sagen Sie mir bitte, welches Thema für Sie am besten passt",
    "optionen": {
      "Forschung & Entwicklung": "taxable_in_germany",
      "Gebäude- und Energiesanierung": "taxable_in_germany",
      "Existenzgründung": "taxable_in_germany",
      "Maschinenfinanzierung": "taxable_in_germany",
      "Erneuerbare Energien": "taxable_in_germany"
    }
  },

  "taxable_in_germany": {
    "frage": "Ist das Unternehmen in Deutschland steuerpflichtig?",
    "optionen": {
      "Ja": "location",
      "Nein": "location"
    }
  },

  "location": {
    "frage": "In welchem Bundesland ist das Unternehmen ansässig?",
    "select": {
      "choices": [
        "Baden-Württemberg",
        "Bayern",
        "Berlin",
        "Brandenburg",
        "Bremen",
        "Hamburg",
        "Hessen",
        "Mecklenburg-Vorpommern",
        "Niedersachsen",
        "Nordrhein-Westfalen",
        "Rheinland-Pfalz",
        "Saarland",
        "Sachsen",
        "Sachsen-Anhalt",
        "Schleswig-Holstein",
        "Thüringen"
      ],
      "next": "company_founded"
    }
  },

  "company_founded": {
    "frage": "In welchem Jahr wurde das Unternehmen gegründet?",
    "optionen": {
      "Weiter": "retrospective_costs"
    }
  },

  "retrospective_costs": {
    "frage": "Hatten Sie seit 2020 bereits Kosten für Forschung und Entwicklung? Wenn ja, wie hoch waren diese (in EUR)?",
    "optionen": {
      "Weiter": "industry"
    }
  },

  "industry": {
    "frage": "In welcher Branche sind Sie aktiv?",
    "optionen": {
      "Weiter": "project_description"
    }
  },

  "project_description": {
    "frage": "Bitte beschreiben Sie in einigen Sätzen das Projekt, für das Sie eine Förderung beantragen möchten, möglichst genau. Zum Beispiel:\n\n- Was wollen Sie gründen, entwickeln, erforschen, sanieren, oder finanzieren?\n- Welche konkreten Schritte planen Sie?",
    "optionen": {
      "Weiter": "project_start"
    }
  },

  "project_start": {
    "frage": "Wann ist bzw. war der Beginn des zu fördernden Projekts?",
    "optionen": {
      "Weiter": "cost"
    }
  },

  "cost": {
    "frage": "Wie hoch sind die Projektkosten (geschätzt in EUR)?",
    "optionen": {
      "Weiter": "own_funds"
    }
  },

  "own_funds": {
    "frage": "Wie viel Eigenanteil davon können Sie aufbringen (in EUR)?",
    "optionen": {
      "Absenden": "chat"
    }
  },

  "chat": {
    "antwort": "✅ Vielen Dank! Anhand Ihrer Angaben suche ich jetzt nach passenden Förderprogrammen.",
    "button_label": "Zum Chat",
    "button_link": "/"
  }
}
